Pycodestyle250ZhongwenWendang/README.md
Pycodestyle250ZhongwenWendang/__init__.py
Pycodestyle250ZhongwenWendang/__main__.py
Pycodestyle250ZhongwenWendang/file.epub
Pycodestyle250ZhongwenWendang/index.html
Pycodestyle250ZhongwenWendang/css/__init__.py
Pycodestyle250ZhongwenWendang/css/annotations.css
Pycodestyle250ZhongwenWendang/css/main.css
Pycodestyle250ZhongwenWendang/css/normalize.css
Pycodestyle250ZhongwenWendang/css/popup.css
Pycodestyle250ZhongwenWendang/font/__init__.py
Pycodestyle250ZhongwenWendang/font/fontello.eot
Pycodestyle250ZhongwenWendang/font/fontello.svg
Pycodestyle250ZhongwenWendang/font/fontello.ttf
Pycodestyle250ZhongwenWendang/font/fontello.woff
Pycodestyle250ZhongwenWendang/img/__init__.py
Pycodestyle250ZhongwenWendang/img/annotator-glyph-sprite.png
Pycodestyle250ZhongwenWendang/img/annotator-icon-sprite.png
Pycodestyle250ZhongwenWendang/img/apple-touch-icon.png
Pycodestyle250ZhongwenWendang/img/cancelfullscreen.png
Pycodestyle250ZhongwenWendang/img/close.png
Pycodestyle250ZhongwenWendang/img/fullscreen.png
Pycodestyle250ZhongwenWendang/img/loader.gif
Pycodestyle250ZhongwenWendang/img/menu-icon.png
Pycodestyle250ZhongwenWendang/img/save.png
Pycodestyle250ZhongwenWendang/img/saved.png
Pycodestyle250ZhongwenWendang/img/settings-s.png
Pycodestyle250ZhongwenWendang/img/settings.png
Pycodestyle250ZhongwenWendang/img/star.png
Pycodestyle250ZhongwenWendang/js/__init__.py
Pycodestyle250ZhongwenWendang/js/epub.js
Pycodestyle250ZhongwenWendang/js/epub.min.js
Pycodestyle250ZhongwenWendang/js/epub.min.map
Pycodestyle250ZhongwenWendang/js/hooks.min.js
Pycodestyle250ZhongwenWendang/js/hooks.min.map
Pycodestyle250ZhongwenWendang/js/reader.js
Pycodestyle250ZhongwenWendang/js/reader.js.map
Pycodestyle250ZhongwenWendang/js/reader.min.js
Pycodestyle250ZhongwenWendang/js/reader.min.map
Pycodestyle250ZhongwenWendang/js/hooks/__init__.py
Pycodestyle250ZhongwenWendang/js/hooks/extensions/__init__.py
Pycodestyle250ZhongwenWendang/js/hooks/extensions/highlight.js
pycodestyle_2_5_0_zhongwen_wendang-2024.3.5.0.dist-info/METADATA
pycodestyle_2_5_0_zhongwen_wendang-2024.3.5.0.dist-info/WHEEL
pycodestyle_2_5_0_zhongwen_wendang-2024.3.5.0.dist-info/entry_points.txt
pycodestyle_2_5_0_zhongwen_wendang-2024.3.5.0.dist-info/top_level.txt
pycodestyle_2_5_0_zhongwen_wendang-2024.3.5.0.dist-info/RECORD
